<mujoco model="anymal_c">
  <compiler angle="radian" assetdir="assets" balanceinertia="true" inertiafromgeom="false"/>

  <option timestep="0.005" density="1.2" viscosity="2e-05"/>

  <size nkey="1"/>

  <visual>
    <quality shadowsize="8192"/>
    <map shadowclip="0.5"/>
  </visual>

  <default>
    <default class="/">
      <material specular="0" shininess="0.25"/>
      <geom contype="0" conaffinity="0" group="1" solref="-1000 -80"/>
      <site size="0.01 0.005 0.005" group="5"/>
      <general forcelimited="true" forcerange="-80 80" biastype="affine" gainprm="80" biasprm="0 -80 -2"/>
      <default class="anymal_c">
        <joint armature="0.01" damping="0.01" frictionloss="0.1"/>
        <default class="visual">
          <geom type="mesh" group="2"/>
          <default class="visual_zflip"/>
        </default>
        <default class="collision">
          <geom type="cylinder" group="3"/>
          <default class="foot">
            <geom size="0.03 0 0" type="sphere" condim="6" priority="1" friction="0.8 0.02 0.01" solimp="0.015 1 0.03"/>
          </default>
        </default>
      </default>
      <default class="reward_collision_sphere">
        <geom group="5" rgba="1 0 0 1"/>
      </default>
    </default>
  </default>

  <asset>
    <texture type="skybox" colorspace="auto" name="//unnamed_texture_0" builtin="gradient" rgb1="0.95 0.95 0.95" rgb2="0.95 0.95 0.95" width="100" height="600"/>
    <texture type="2d" colorspace="auto" name="texplane" builtin="checker" rgb1="0.345 0.575 0.748" rgb2="0.345 0.575 0.748" markrgb="1 1 1" width="512" height="512"/>
    <texture type="2d" colorspace="linear" name="base" file="base.png"/>
    <texture type="2d" colorspace="linear" name="top_shell" file="top_shell.png"/>
    <texture type="2d" colorspace="linear" name="bottom_shell" file="bottom_shell.png"/>
    <texture type="2d" colorspace="linear" name="remote" file="remote.png"/>
    <texture type="2d" colorspace="linear" name="hatch" file="hatch.png"/>
    <texture type="2d" colorspace="linear" name="handle" file="handle.png"/>
    <texture type="2d" colorspace="linear" name="face" file="face.png"/>
    <texture type="2d" colorspace="linear" name="battery" file="battery.png"/>
    <texture type="2d" colorspace="linear" name="lidar_cage" file="lidar_cage.png"/>
    <texture type="2d" colorspace="linear" name="depth_camera" file="depth_camera.png"/>
    <texture type="2d" colorspace="linear" name="wide_angle_camera" file="wide_angle_camera.png"/>
    <texture type="2d" colorspace="linear" name="lidar" file="lidar.png"/>
    <texture type="2d" colorspace="linear" name="drive" file="drive.png"/>
    <texture type="2d" colorspace="linear" name="hip_l" file="hip_l.png"/>
    <texture type="2d" colorspace="linear" name="shank_l" file="shank_l.png"/>
    <texture type="2d" colorspace="linear" name="foot" file="foot.png"/>
    <texture type="2d" colorspace="linear" name="thigh" file="thigh.png"/>
    <texture type="2d" colorspace="linear" name="shank_r" file="shank_r.png"/>
    <texture type="2d" colorspace="linear" name="hip_r" file="hip_r.png"/>
    <material name="MatPlane" class="/" texture="texplane" texuniform="true" texrepeat="2 2" specular="0.9" shininess="0.5"/>
    <material name="black_plastic" class="/" rgba="0.007 0.007 0.007 1"/>
    <material name="green" class="/" rgba="0.052 0.178 0.033 1"/>
    <material name="red" class="/" rgba="0.178 0.006 0.005 1"/>
    <material name="yellow" class="/" rgba="0.178 0.119 0.006 1"/>
    <material name="lwl" class="/" rgba="0.8 0.8 0.8 1"/>
    <material name="base" class="/" texture="base"/>
    <material name="top_shell" class="/" texture="top_shell"/>
    <material name="bottom_shell" class="/" texture="bottom_shell"/>
    <material name="hip_l" class="/" texture="hip_l"/>
    <material name="thigh" class="/" texture="thigh"/>
    <material name="shank_l" class="/" texture="shank_l"/>
    <material name="foot" class="/" texture="foot"/>
    <material name="hip_r" class="/" texture="hip_r"/>
    <material name="shank" class="/" texture="shank_r"/>
    <material name="hatch" class="/" texture="hatch"/>
    <material name="remote" class="/" texture="remote"/>
    <material name="handle" class="/" texture="handle"/>
    <material name="face" class="/" texture="face"/>
    <material name="depth_camera" class="/" texture="depth_camera"/>
    <material name="wide_angle_camera" class="/" texture="wide_angle_camera"/>
    <material name="battery" class="/" texture="battery"/>
    <material name="lidar_cage" class="/" texture="lidar_cage"/>
    <material name="lidar" class="/" texture="lidar"/>
    <material name="drive" class="/" texture="drive"/>
    <mesh name="base_0" class="/" file="base_0.obj"/>
    <mesh name="base_1" class="/" file="base_1.obj"/>
    <mesh name="base_2" class="/" file="base_2.obj"/>
    <mesh name="base_3" class="/" file="base_3.obj"/>
    <mesh name="base_4" class="/" file="base_4.obj"/>
    <mesh name="base_5" class="/" file="base_5.obj"/>
    <mesh name="top_shell" class="/" file="top_shell.obj"/>
    <mesh name="bottom_shell" class="/" file="bottom_shell.obj"/>
    <mesh name="remote" class="/" file="remote.obj"/>
    <mesh name="handle" class="/" file="handle.obj"/>
    <mesh name="face" class="/" file="face.obj"/>
    <mesh name="wide_angle_camera" class="/" file="wide_angle_camera.obj"/>
    <mesh name="depth_camera" class="/" file="depth_camera.obj"/>
    <mesh name="battery" class="/" file="battery.obj"/>
    <mesh name="lidar_cage" class="/" file="lidar_cage.obj"/>
    <mesh name="lidar" class="/" file="lidar.obj"/>
    <mesh name="drive" class="/" file="drive.obj"/>
    <mesh name="hip_l" class="/" file="hip_l.obj"/>
    <mesh name="thigh" class="/" file="thigh.obj"/>
    <mesh name="shank_l" class="/" file="shank_l.obj"/>
    <mesh name="foot" class="/" file="foot.obj"/>
    <mesh name="hip_r" class="/" file="hip_r.obj"/>
    <mesh name="hatch" class="/" file="hatch.obj"/>
    <mesh name="shank_r" class="/" file="shank_r.obj"/>
  </asset>

  <worldbody>
    <geom name="floor" class="/" size="100 100 0.125" type="plane" group="0" material="MatPlane"/>
    <light name="toplight_shadow" class="/" pos="0 0 5" dir="0.0990148 0.0990148 -0.990148" type="directional" ambient="0.04 0.04 0.04" diffuse="0.55 0.55 0.55" specular="0.12 0.12 0.12"/>
    <light name="toplight_fill" class="/" pos="0 0 5" dir="0.0990148 0.0990148 -0.990148" type="directional" castshadow="false" ambient="0.04 0.04 0.04" diffuse="0.3 0.3 0.3" specular="0.08 0.08 0.08"/>
    <body name="trunk" childclass="anymal_c" pos="-0.00172008 0.000789806 -0.00267339" quat="0.999999 -0.000452507 -0.000138475 -0.000991013">
      <inertial pos="-0.000617601 0.00235812 0.0477979" quat="0.498488 0.50205 0.497446 0.502" mass="14.6531" diaginertia="0.362869 0.311147 0.177214"/>
      <joint name="//unnamed_joint_0" type="free" armature="0" damping="0" frictionloss="0"/>
      <geom name="//unnamed_geom_1" class="visual" material="green" mesh="base_0"/>
      <geom name="//unnamed_geom_2" class="visual" material="yellow" mesh="base_1"/>
      <geom name="//unnamed_geom_3" class="visual" material="red" mesh="base_2"/>
      <geom name="//unnamed_geom_4" class="visual" material="black_plastic" mesh="base_3"/>
      <geom name="//unnamed_geom_5" class="visual" material="lwl" mesh="base_4"/>
      <geom name="//unnamed_geom_6" class="visual" material="base" mesh="base_5"/>
      <geom name="trunk_1" class="collision" size="0.263377 0.0635739 0.0817378" type="box"/>
      <geom name="trunk_2" class="collision" size="0.0817378 0.0658444" pos="0.193965 0.0610427 0" quat="0.707107 0 0.707107 0"/>
      <geom name="trunk_3" class="collision" size="0.0817378 0.0658444" pos="-0.193965 0.0610427 0" quat="0.707107 0 0.707107 0"/>
      <geom name="trunk_4" class="collision" size="0.0817378 0.0658444" pos="0.193965 -0.0610427 0" quat="0.707107 0 0.707107 0"/>
      <geom name="trunk_5" class="collision" size="0.0817378 0.0658444" pos="-0.193965 -0.0610427 0" quat="0.707107 0 0.707107 0"/>
      <geom name="//unnamed_geom_12" class="visual" material="top_shell" mesh="top_shell"/>
      <geom name="//unnamed_geom_13" class="visual" material="bottom_shell" mesh="bottom_shell"/>
      <geom name="//unnamed_geom_14" class="visual" material="remote" mesh="remote"/>
      <geom name="//unnamed_geom_15" class="visual" material="handle" mesh="handle"/>
      <geom name="//unnamed_geom_16" class="visual" pos="0.369648 0 0" quat="1 0 0 0" material="face" mesh="face"/>
      <geom name="trunk_6" class="collision" size="0.0499509 0.0635739 0.0817378" pos="0.418697 0 0" type="box"/>
      <geom name="//unnamed_geom_18" class="collision" size="0.0817378 0.0499509" pos="0.418697 0.0610427 0" quat="0.707107 0 0.707107 0"/>
      <geom name="//unnamed_geom_19" class="collision" size="0.0817378 0.0499509" pos="0.418697 -0.0610427 0" quat="0.707107 0 0.707107 0"/>
      <geom name="//unnamed_geom_20" class="visual" pos="0.411699 0 -0.0285785" quat="0.965926 0 0.258819 0" material="depth_camera" mesh="depth_camera"/>
      <geom name="//unnamed_geom_21" class="visual" pos="0.457489 0 0.0143826" material="wide_angle_camera" mesh="wide_angle_camera"/>
      <geom name="//unnamed_geom_22" class="visual_zflip" pos="-0.369648 0 0" quat="0 0 0 1" material="face" mesh="face"/>
      <geom name="trunk_7" class="collision" size="0.0499509 0.0635739 0.0817378" pos="-0.418697 0 0" quat="0 0 0 1" type="box"/>
      <geom name="//unnamed_geom_24" class="collision" size="0.0817378 0.0499509" pos="-0.418697 -0.0610427 0" quat="0 -0.707107 0 0.707107"/>
      <geom name="//unnamed_geom_25" class="collision" size="0.0817378 0.0499509" pos="-0.418697 0.0610427 0" quat="0 -0.707107 0 0.707107"/>
      <geom name="//unnamed_geom_26" class="visual" pos="-0.411699 0 -0.0285785" quat="0 -0.258819 0 0.965926" material="depth_camera" mesh="depth_camera"/>
      <geom name="//unnamed_geom_27" class="visual_zflip" pos="-0.457489 0 0.0143826" quat="0 0 0 1" material="wide_angle_camera" mesh="wide_angle_camera"/>
      <geom name="//unnamed_geom_28" class="visual" material="battery" mesh="battery"/>
      <geom name="//unnamed_geom_29" class="visual" pos="0 0.0664197 0.027386" quat="0.683013 -0.183013 0.183013 0.683013" material="depth_camera" mesh="depth_camera"/>
      <geom name="//unnamed_geom_30" class="visual" pos="0 -0.0664197 0.027386" quat="0.683013 0.183013 0.183013 -0.683013" material="depth_camera" mesh="depth_camera"/>
      <geom name="//unnamed_geom_31" class="visual" pos="-0.324612 0 0.0706162" quat="1 0 0 0" material="lidar_cage" mesh="lidar_cage"/>
      <geom name="trunk_8" class="collision" size="0.0635739 0.0544919" pos="-0.324612 0 0.128262"/>
      <geom name="//unnamed_geom_33" class="visual" pos="-0.324612 -7.761e-06 0.136621" quat="0.707107 0 0 -0.707107" material="lidar" mesh="lidar"/>
      <geom name="//unnamed_geom_34" class="visual" pos="0.267449 0.0907235 -1.53054e-09" quat="0.258819 0.965926 0 0" material="drive" mesh="drive"/>
      <geom name="//unnamed_geom_35" class="visual" pos="0.267449 -0.0907235 1.53054e-09" quat="0.258819 -0.965926 0 0" material="drive" mesh="drive"/>
      <geom name="//unnamed_geom_36" class="visual" pos="-0.267449 0.0907235 1.53054e-09" quat="0 0 0.965926 -0.258819" material="drive" mesh="drive"/>
      <geom name="//unnamed_geom_37" class="visual" pos="-0.267449 -0.0907235 -1.53054e-09" quat="0 0 -0.965926 -0.258819" material="drive" mesh="drive"/>
      <geom name="//unnamed_geom_38" class="visual" pos="0.103448 0 0.0701358" quat="1 0 0 0" material="hatch" mesh="hatch"/>
      <geom name="//unnamed_geom_39" class="reward_collision_sphere" size="0.108984"/>
      <geom name="//unnamed_geom_40" class="reward_collision_sphere" size="0.108984" pos="0.401307 0 0"/>
      <geom name="//unnamed_geom_41" class="reward_collision_sphere" size="0.108984" pos="-0.401307 0 0"/>
      <site name="imu" pos="0.234537 0.0168401 0.0310276" size="0.00908198"/>
      <camera name="track" pos="0 -1.74408 0" quat="0.707107 0.707107 0 0" mode="trackcom"/>
      <camera name="ego_camera" pos="0.401307 0 -0.0384306" quat="-0.5 -0.5 0.5 0.5"/>
      <body name="LF_HIP" pos="0.267145 0.0902477 -0.000471202" quat="0.259047 0.965864 0.000368375 -0.000549209">
        <inertial pos="0.0479725 -0.0134787 -0.00997813" quat="-0.125076 0.711646 -0.128052 0.679352" mass="2.07174" diaginertia="0.00327095 0.00246534 0.00276446"/>
        <joint name="LF_HAA" pos="0 0 0" axis="0.999898 -0.00300948 -0.0139347" range="-0.725796 0.488127" armature="0.00975601" damping="0.008191" frictionloss="0.0864152"/>
        <geom name="//unnamed_geom_42" class="visual" pos="0 -9.00349e-05 1.47882e-05" quat="0.258819 -0.965926 0 0" material="hip_l" mesh="hip_l"/>
        <geom name="//unnamed_geom_43" class="visual" pos="0.0534184 -0.0644991 -0.0378949" quat="0.183013 -0.683013 0.683013 0.183013" material="drive" mesh="drive"/>
        <geom name="//unnamed_geom_44" class="collision" size="0.0454099 0.0635739" pos="0.0534184 -0.0104294 -0.00663408" quat="-0.353553 -0.612372 0.612372 -0.353553"/>
        <body name="LF_THIGH" pos="0.0536412 -0.0641411 -0.0446161" quat="0.182709 -0.683339 0.682835 0.182761">
          <inertial pos="0.0286433 0.000468752 -0.234084" quat="0.99357 -0.0146954 -0.0815817 0.0771234" mass="2.24022" diaginertia="0.0171501 0.0144487 0.00345478"/>
          <joint name="LF_HFE" pos="0 0 0" axis="0.999979 -0.00380723 0.00524685" stiffness="0.0133408" range="-3.1346 3.11146" armature="0.00795185" damping="0.0123438" frictionloss="0.0909598"/>
          <geom name="//unnamed_geom_45" class="visual" pos="0.000393037 6.19334e-07 0" quat="0.707107 0 0 -0.707107" material="thigh" mesh="thigh"/>
          <geom name="//unnamed_geom_46" class="collision" size="0.0590329 0.0363279" pos="0.0356717 0 0" quat="0.5 0.5 -0.5 -0.5"/>
          <geom name="//unnamed_geom_47" class="collision" size="0.0340574 0.0272459 0.128341" pos="0.0267538 0 -0.135769" quat="0.707107 0 0 -0.707107" type="box"/>
          <geom name="//unnamed_geom_48" class="visual" pos="0.0894468 0 -0.273818" quat="1 0 0 0" material="drive" mesh="drive"/>
          <geom name="//unnamed_geom_49" class="collision" size="0.0454099 0.0635739" pos="0.0270213 0 -0.273818" quat="0.707107 0 0.707107 0"/>
          <geom name="//unnamed_geom_50" class="reward_collision_sphere" size="0.0726559" pos="0.0222948 0 0"/>
          <body name="LF_SHANK" pos="0.0873387 -0.00122359 -0.272008" quat="1 2.56191e-06 -3.38342e-05 8.22928e-05">
            <inertial pos="0.00255478 -0.0558706 -0.0756089" quat="0.992984 -0.115768 -0.0025969 -0.0239577" mass="0.433932" diaginertia="0.00580024 0.00449578 0.000910968"/>
            <joint name="LF_KFE" pos="0 0 0" axis="0.999996 -2.19677e-05 -0.0029022" stiffness="0.00475045" range="-3.10004 3.13543" armature="0.00901452" damping="0.00924471" frictionloss="0.0886217"/>
            <geom name="//unnamed_geom_51" class="visual" pos="0.000128161 0.000683359 0" quat="0.707107 0 0 -0.707107" material="shank_l" mesh="shank_l"/>
            <geom name="LF_kfe_act" class="collision" size="0.0544919 0.018164" pos="0.0178358 0 0" quat="0.5 0.5 -0.5 -0.5"/>
            <geom name="//unnamed_geom_53" class="collision" size="0.0522205 0.0306517 0.0172558" pos="0.0178358 -0.0501413 0" quat="0.5 0.5 -0.5 -0.5" type="box"/>
            <geom name="//unnamed_geom_54" class="visual" pos="0.0116379 -0.0764755 -0.32471" quat="0.382683 0 0 -0.92388" material="foot" mesh="foot"/>
            <geom name="LF_calf" class="collision" size="0.0158935 0.128285" pos="0.0116379 -0.0766957 -0.162355" quat="0.707107 0 0 -0.707107"/>
            <geom name="LF_foot" class="foot" size="0.0283814" pos="0.0116379 -0.0766957 -0.303092" quat="0.707107 0 0 -0.707107"/>
            <geom name="//unnamed_geom_57" class="reward_collision_sphere" size="0.0908198" pos="-0.0445896 0 0"/>
            <geom name="//unnamed_geom_58" class="reward_collision_sphere" size="0.0454099" pos="0.0116379 -0.0766957 -0.303092"/>
            <site name="LF_foot" class="foot" pos="0.0116379 -0.0766957 -0.303092" quat="0.707107 0 0 -0.707107" size="0.00908198"/>
          </body>
        </body>
      </body>
      <body name="RF_HIP" pos="0.270653 -0.0882183 -0.000326971" quat="0.25876 -0.965942 7.12209e-05 -0.000358427">
        <inertial pos="0.0485189 0.0117171 -0.00891313" quat="0.134824 0.680536 0.126917 0.708932" mass="2.05366" diaginertia="0.00316446 0.00254157 0.00271305"/>
        <joint name="RF_HAA" pos="0 0 0" axis="0.999997 -0.00158006 0.0020091" range="-0.460759 0.709865" armature="0.00889234" damping="0.00947963" frictionloss="0.102669"/>
        <geom name="//unnamed_geom_59" class="visual" pos="0 9.00342e-05 1.47881e-05" quat="0.258819 0.965926 0 0" material="hip_r" mesh="hip_r"/>
        <geom name="//unnamed_geom_60" class="visual" pos="0.0534184 0.0644991 -0.0378949" quat="0.183013 0.683013 0.683013 -0.183013" material="drive" mesh="drive"/>
        <geom name="//unnamed_geom_61" class="collision" size="0.0454099 0.0635739" pos="0.0534184 0.0104294 -0.00663408" quat="-0.353553 0.612372 0.612372 0.353553"/>
        <body name="RF_THIGH" pos="0.0564142 0.0631951 -0.0418587" quat="0.183021 0.683009 0.682798 -0.183818">
          <inertial pos="0.0270239 0.000105437 -0.235041" quat="0.993121 -0.015039 -0.0790154 0.0850985" mass="2.35146" diaginertia="0.016362 0.0149258 0.00339042"/>
          <joint name="RF_HFE" pos="0 0 0" axis="0.99994 0.0062815 0.00892011" stiffness="0.00719735" range="-3.12802 3.16049" armature="0.00866019" damping="0.0103606" frictionloss="0.0991622"/>
          <geom name="//unnamed_geom_62" class="visual" pos="0.000393037 6.19334e-07 0" quat="0.707107 0 0 -0.707107" material="thigh" mesh="thigh"/>
          <geom name="//unnamed_geom_63" class="collision" size="0.0590329 0.0363279" pos="0.0356717 0 0" quat="0.5 0.5 0.5 0.5"/>
          <geom name="//unnamed_geom_64" class="collision" size="0.0340574 0.0272459 0.128341" pos="0.0267538 0 -0.135769" quat="0.707107 0 0 0.707107" type="box"/>
          <geom name="//unnamed_geom_65" class="visual" pos="0.0894468 0 -0.273818" quat="1 0 0 0" material="drive" mesh="drive"/>
          <geom name="//unnamed_geom_66" class="collision" size="0.0454099 0.0635739" pos="0.0270213 0 -0.273818" quat="0.707107 0 0.707107 0"/>
          <geom name="//unnamed_geom_67" class="reward_collision_sphere" size="0.0726559" pos="0.0222948 0 0"/>
          <body name="RF_SHANK" pos="0.0894666 -0.000147668 -0.272167" quat="1 0.000138579 -0.000252687 -6.16833e-05">
            <inertial pos="0.00686884 0.0524262 -0.0796367" quat="0.993945 0.105864 0.00620756 0.0287823" mass="0.445774" diaginertia="0.00609389 0.00468172 0.000943282"/>
            <joint name="RF_KFE" pos="0 0 0" axis="0.99999 -0.00359055 -0.00256211" range="-3.14924 3.08518" armature="0.00974202" damping="0.00864533" frictionloss="0.0899667"/>
            <geom name="//unnamed_geom_68" class="visual" pos="0.00012816 -0.000683358 0" quat="0.707107 0 0 0.707107" material="shank" mesh="shank_r"/>
            <geom name="RF_kfe_act" class="collision" size="0.0544919 0.018164" pos="0.0178358 0 0" quat="0.5 0.5 0.5 0.5"/>
            <geom name="//unnamed_geom_70" class="collision" size="0.0522205 0.0306517 0.0172558" pos="0.0178358 0.0501413 0" quat="0.5 0.5 0.5 0.5" type="box"/>
            <geom name="//unnamed_geom_71" class="visual" pos="0.0116379 0.0764755 -0.32471" quat="0.382683 0 0 0.92388" material="foot" mesh="foot"/>
            <geom name="RF_calf" class="collision" size="0.0158935 0.128285" pos="0.0116379 0.0766957 -0.162355" quat="0.707107 0 0 0.707107"/>
            <geom name="RF_foot" class="foot" size="0.0295586" pos="0.0116379 0.0766957 -0.303092" quat="0.707107 0 0 0.707107"/>
            <geom name="//unnamed_geom_74" class="reward_collision_sphere" size="0.0908198" pos="-0.0445896 0 0"/>
            <geom name="//unnamed_geom_75" class="reward_collision_sphere" size="0.0454099" pos="0.0116379 0.0766957 -0.303092"/>
            <site name="RF_foot" class="foot" pos="0.0116379 0.0766957 -0.303092" quat="0.707107 0 0 0.707107" size="0.00908198"/>
          </body>
        </body>
      </body>
      <body name="LH_HIP" pos="-0.267481 0.0886314 0.000764395" quat="-0.00047314 -0.000241388 0.966027 -0.25844">
        <inertial pos="0.0499748 0.0132688 -0.00781544" quat="0.136753 0.67786 0.125834 0.711316" mass="2.06568" diaginertia="0.003302 0.00240613 0.00266852"/>
        <joint name="LH_HAA" pos="0 0 0" axis="0.999998 -9.99133e-05 -0.002137" range="-0.5225 0.718671" armature="0.0091214" damping="0" frictionloss="0.0903429"/>
        <geom name="//unnamed_geom_76" class="visual" pos="0 9.00342e-05 1.47881e-05" quat="-0.258819 -0.965926 0 0" material="hip_r" mesh="hip_r"/>
        <geom name="//unnamed_geom_77" class="visual" pos="0.0534184 0.0644991 -0.0378949" quat="0.183013 0.683013 0.683013 -0.183013" material="drive" mesh="drive"/>
        <geom name="//unnamed_geom_78" class="collision" size="0.0454099 0.0635739" pos="0.0534184 0.0104294 -0.00663408" quat="-0.353553 0.612372 0.612372 0.353553"/>
        <body name="LH_THIGH" pos="0.051769 0.0621664 -0.0395938" quat="0.183094 0.683027 0.683012 -0.182882">
          <inertial pos="0.0273967 0.000748651 -0.234125" quat="0.99277 -0.00513547 -0.0806622 0.088736" mass="2.33763" diaginertia="0.0177987 0.0154017 0.00355398"/>
          <joint name="LH_HFE" pos="0 0 0" axis="0.999999 0.001377 0.000871408" range="-3.13893 3.10566" armature="0.0102788" damping="0.0201132" frictionloss="0.094826"/>
          <geom name="//unnamed_geom_79" class="visual" pos="0.000393037 6.19334e-07 0" quat="0.707107 0 0 -0.707107" material="thigh" mesh="thigh"/>
          <geom name="//unnamed_geom_80" class="collision" size="0.0590329 0.0363279" pos="0.0356717 0 0" quat="0.5 0.5 -0.5 -0.5"/>
          <geom name="//unnamed_geom_81" class="collision" size="0.0340574 0.0272459 0.128341" pos="0.0267538 0 -0.135769" quat="0.707107 0 0 -0.707107" type="box"/>
          <geom name="//unnamed_geom_82" class="visual" pos="0.0894468 0 -0.273818" quat="1 0 0 0" material="drive" mesh="drive"/>
          <geom name="//unnamed_geom_83" class="collision" size="0.0454099 0.0635739" pos="0.0270213 0 -0.273818" quat="0.707107 0 0.707107 0"/>
          <geom name="//unnamed_geom_84" class="reward_collision_sphere" size="0.0726559" pos="0.0222948 0 0"/>
          <body name="LH_SHANK" pos="0.0875402 0.00208532 -0.275264" quat="1 4.51479e-05 0.000107332 2.97486e-05">
            <inertial pos="0.00738306 0.0509638 -0.075532" quat="0.993488 0.111427 0.000531435 0.0237601" mass="0.432851" diaginertia="0.00571276 0.00482145 0.00088638"/>
            <joint name="LH_KFE" pos="0 0 0" axis="0.999903 -0.00759437 0.0116435" stiffness="0.00938503" range="-3.09433 3.14213" armature="0.00931039" damping="0.013592" frictionloss="0.101835"/>
            <geom name="//unnamed_geom_85" class="visual" pos="0.00012816 -0.000683358 0" quat="-0.707107 0 0 -0.707107" material="shank" mesh="shank_r"/>
            <geom name="LH_kfe_act" class="collision" size="0.0544919 0.018164" pos="0.0178358 0 0" quat="0.5 0.5 -0.5 -0.5"/>
            <geom name="//unnamed_geom_87" class="collision" size="0.0522205 0.0306517 0.0172558" pos="0.0178358 0.0501413 0" quat="0.5 0.5 -0.5 -0.5" type="box"/>
            <geom name="//unnamed_geom_88" class="visual" pos="0.0116379 0.0764755 -0.32471" quat="-0.382683 0 0 -0.92388" material="foot" mesh="foot"/>
            <geom name="LH_calf" class="collision" size="0.0158935 0.128285" pos="0.0116379 0.0766957 -0.162355" quat="0.707107 0 0 -0.707107"/>
            <geom name="LH_foot" class="foot" size="0.0311926" pos="0.0116379 0.0766957 -0.303092" quat="0.707107 0 0 -0.707107"/>
            <geom name="//unnamed_geom_91" class="reward_collision_sphere" size="0.0908198" pos="-0.0445896 0 0"/>
            <geom name="//unnamed_geom_92" class="reward_collision_sphere" size="0.0454099" pos="0.0116379 0.0766957 -0.303092"/>
            <site name="LH_foot" class="foot" pos="0.0116379 0.0766957 -0.303092" quat="0.707107 0 0 -0.707107" size="0.00908198"/>
          </body>
        </body>
      </body>
      <body name="RH_HIP" pos="-0.267323 -0.0939098 0.00065368" quat="-0.000792018 -0.000553234 -0.965789 -0.259329">
        <inertial pos="0.0496071 -0.0133444 -0.00986322" quat="-0.127925 0.709694 -0.135336 0.679451" mass="2.19272" diaginertia="0.00331143 0.00247637 0.00274426"/>
        <joint name="RH_HAA" pos="0 0 0" axis="0.999945 0.00495031 -0.00921101" range="-0.671848 0.472967" armature="0.00796472" damping="0.0063472" frictionloss="0.103004"/>
        <geom name="//unnamed_geom_93" class="visual" pos="0 -9.00349e-05 1.47882e-05" quat="-0.258819 0.965926 0 0" material="hip_l" mesh="hip_l"/>
        <geom name="//unnamed_geom_94" class="visual" pos="0.0534184 -0.0644991 -0.0378949" quat="-0.183013 0.683013 -0.683013 -0.183013" material="drive" mesh="drive"/>
        <geom name="//unnamed_geom_95" class="collision" size="0.0454099 0.0635739" pos="0.0534184 -0.0104294 -0.00663408" quat="0.353553 0.612372 -0.612372 0.353553"/>
        <body name="RH_THIGH" pos="0.0550113 -0.0617146 -0.0406408" quat="-0.183116 0.682702 -0.683302 -0.18299">
          <inertial pos="0.0254082 0.00167769 -0.235574" quat="0.993411 -0.00574348 -0.0793105 0.08253" mass="2.25199" diaginertia="0.0174695 0.014924 0.00343008"/>
          <joint name="RH_HFE" pos="0 0 0" axis="0.999892 0.0137593 -0.00511956" stiffness="0.0015982" range="-3.12756 3.14016" armature="0.00875098" damping="0.00595844" frictionloss="0.0874096"/>
          <geom name="//unnamed_geom_96" class="visual" pos="0.000393037 6.19334e-07 0" quat="0.707107 0 0 -0.707107" material="thigh" mesh="thigh"/>
          <geom name="//unnamed_geom_97" class="collision" size="0.0590329 0.0363279" pos="0.0356717 0 0" quat="0.5 0.5 0.5 0.5"/>
          <geom name="//unnamed_geom_98" class="collision" size="0.0340574 0.0272459 0.128341" pos="0.0267538 0 -0.135769" quat="0.707107 0 0 0.707107" type="box"/>
          <geom name="//unnamed_geom_99" class="visual" pos="0.0894468 0 -0.273818" quat="1 0 0 0" material="drive" mesh="drive"/>
          <geom name="//unnamed_geom_100" class="collision" size="0.0454099 0.0635739" pos="0.0270213 0 -0.273818" quat="0.707107 0 0.707107 0"/>
          <geom name="//unnamed_geom_101" class="reward_collision_sphere" size="0.0726559" pos="0.0222948 0 0"/>
          <body name="RH_SHANK" pos="0.0883892 -0.000375862 -0.273967" quat="1 0.00021874 0.000548137 0.000129407">
            <inertial pos="0.00767498 -0.0531585 -0.0778033" quat="0.993246 -0.11349 0.00264785 -0.0239863" mass="0.422069" diaginertia="0.00546834 0.00455322 0.000886868"/>
            <joint name="RH_KFE" pos="0 0 0" axis="0.999958 0.0088011 -0.00245459" range="-3.12297 3.18476" armature="0.00795888" damping="0.015633" frictionloss="0.0948366"/>
            <geom name="//unnamed_geom_102" class="visual" pos="0.000128161 0.000683359 0" quat="0.707107 0 0 -0.707107" material="shank_l" mesh="shank_l"/>
            <geom name="RH_kfe_act" class="collision" size="0.0544919 0.018164" pos="0.0178358 0 0" quat="0.5 0.5 0.5 0.5"/>
            <geom name="//unnamed_geom_104" class="collision" size="0.0522205 0.0306517 0.0172558" pos="0.0178358 -0.0501413 0" quat="0.5 0.5 0.5 0.5" type="box"/>
            <geom name="//unnamed_geom_105" class="visual" pos="0.0116379 -0.0764755 -0.32471" quat="0.382683 0 0 -0.92388" material="foot" mesh="foot"/>
            <geom name="RH_calf" class="collision" size="0.0158935 0.128285" pos="0.0116379 -0.0766957 -0.162355" quat="0.707107 0 0 0.707107"/>
            <geom name="RH_foot" class="foot" size="0.021267" pos="0.0116379 -0.0766957 -0.303092" quat="0.707107 0 0 0.707107"/>
            <geom name="//unnamed_geom_108" class="reward_collision_sphere" size="0.0908198" pos="-0.0445896 0 0"/>
            <geom name="//unnamed_geom_109" class="reward_collision_sphere" size="0.0454099" pos="0.0116379 -0.0766957 -0.303092"/>
            <site name="RH_foot" class="foot" pos="0.0116379 -0.0766957 -0.303092" quat="0.707107 0 0 0.707107" size="0.00908198"/>
          </body>
        </body>
      </body>
    </body>
  </worldbody>

  <contact>
    <pair class="/" geom1="floor" geom2="LF_foot" name="//unnamed_contact_0"/>
    <pair class="/" geom1="floor" geom2="RF_foot" name="//unnamed_contact_1"/>
    <pair class="/" geom1="floor" geom2="LH_foot" name="//unnamed_contact_2"/>
    <pair class="/" geom1="floor" geom2="RH_foot" name="//unnamed_contact_3"/>
  </contact>

  <actuator>
    <general name="LF_HAA" class="/" joint="LF_HAA" forcerange="-79.4788 79.4788" gainprm="66.172" biasprm="0 -66.172 -1.79496"/>
    <general name="LF_HFE" class="/" joint="LF_HFE" forcerange="-73.8269 73.8269" gainprm="66.172" biasprm="0 -66.172 -1.79496"/>
    <general name="LF_KFE" class="/" joint="LF_KFE" forcerange="-72.3376 72.3376" gainprm="66.172" biasprm="0 -66.172 -1.79496"/>
    <general name="RF_HAA" class="/" joint="RF_HAA" forcerange="-74.3247 74.3247" gainprm="66.172" biasprm="0 -66.172 -1.79496"/>
    <general name="RF_HFE" class="/" joint="RF_HFE" forcerange="-80.2082 80.2082" gainprm="66.172" biasprm="0 -66.172 -1.79496"/>
    <general name="RF_KFE" class="/" joint="RF_KFE" forcerange="-66.3737 66.3737" gainprm="66.172" biasprm="0 -66.172 -1.79496"/>
    <general name="LH_HAA" class="/" joint="LH_HAA" forcerange="-71.5509 71.5509" gainprm="66.172" biasprm="0 -66.172 -1.79496"/>
    <general name="LH_HFE" class="/" joint="LH_HFE" forcerange="-80.6824 80.6824" gainprm="66.172" biasprm="0 -66.172 -1.79496"/>
    <general name="LH_KFE" class="/" joint="LH_KFE" forcerange="-73.1396 73.1396" gainprm="66.172" biasprm="0 -66.172 -1.79496"/>
    <general name="RH_HAA" class="/" joint="RH_HAA" forcerange="-72.0494 72.0494" gainprm="66.172" biasprm="0 -66.172 -1.79496"/>
    <general name="RH_HFE" class="/" joint="RH_HFE" forcerange="-77.1068 77.1068" gainprm="66.172" biasprm="0 -66.172 -1.79496"/>
    <general name="RH_KFE" class="/" joint="RH_KFE" forcerange="-70.2365 70.2365" gainprm="66.172" biasprm="0 -66.172 -1.79496"/>
  </actuator>

  <sensor>
    <gyro site="imu" name="imu_angular_velocity"/>
    <velocimeter site="imu" name="imu_linear_velocity"/>
    <framelinvel objtype="site" objname="LF_foot" name="LF_foot_global_linear_velocity"/>
    <framelinvel objtype="site" objname="RF_foot" name="RF_foot_global_linear_velocity"/>
    <framelinvel objtype="site" objname="LH_foot" name="LH_foot_global_linear_velocity"/>
    <framelinvel objtype="site" objname="RH_foot" name="RH_foot_global_linear_velocity"/>
  </sensor>

  <keyframe>
    <key name="home" qpos="0 0 0.55 1 0 0 0 0 0.4 -0.8 0 -0.4 0.8 0 -0.4 0.8 0 0.4 -0.8"/>
  </keyframe>
</mujoco>
